[
    {
     "站代號": "D434A",
     "站名": "梅山站",
     "郵遞區號": "603",
     "地址": "嘉義縣梅山鄉梅北村中山路746號",
     "地區": "嘉義縣梅山鄉",
     "經度": 120.545277777777,
     "緯度": 23.59,
     "電話": "(05)2622821",
     "服務類型": "Gogoro電動機車換電",
     "提供服務時段": "07:00-21:00"
    },
    {
     "站代號": "D434E",
     "站名": "太保站",
     "郵遞區號": "612",
     "地址": "嘉義縣太保市春珠里春珠178號",
     "地區": "嘉義縣太保市",
     "經度": 120.339166666666,
     "緯度": 23.4525,
     "電話": "(05)3711635",
     "服務類型": "電動機車充電",
     "提供服務時段": "07:00-21:00"
    },
    {
     "站代號": "D434E",
     "站名": "太保站",
     "郵遞區號": "612",
     "地址": "嘉義縣太保市春珠里春珠178號",
     "地區": "嘉義縣太保市",
     "經度": 120.339166666666,
     "緯度": 23.4525,
     "電話": "(05)3711635",
     "服務類型": "光陽電動機車換電2.0",
     "提供服務時段": "07:00-21:00"
    },
    {
     "站代號": "D434F",
     "站名": "六腳站",
     "郵遞區號": "615",
     "地址": "嘉義縣六腳鄉六腳村六腳路2-15號",
     "地區": "嘉義縣六腳鄉",
     "經度": 120.257777777777,
     "緯度": 23.5127777777777,
     "電話": "(05)3781175",
     "服務類型": "光陽電動機車換電3.0",
     "提供服務時段": "07:00-21:00"
    },
    {
     "站代號": "D434G",
     "站名": "蒜頭站",
     "郵遞區號": "615",
     "地址": "嘉義縣六腳鄉蒜頭村1-15號",
     "地區": "嘉義縣六腳鄉",
     "經度": 120.293333333333,
     "緯度": 23.4961111111111,
     "電話": "(05)3802944",
     "服務類型": "光陽電動機車換電2.0",
     "提供服務時段": "07:00-21:00"
    },
    {
     "站代號": "D434H",
     "站名": "布袋站",
     "郵遞區號": "625",
     "地址": "嘉義縣布袋鎮興中里上海路1號",
     "地區": "嘉義縣布袋鎮",
     "經度": 120.166944444444,
     "緯度": 23.3794444444444,
     "電話": "(05)3471410",
     "服務類型": "光陽電動機車換電2.0",
     "提供服務時段": "07:00-21:00"
    },
    {
     "站代號": "D434K",
     "站名": "朴子山通路站",
     "郵遞區號": "613",
     "地址": "嘉義縣朴子市大鄉里大槺榔625號",
     "地區": "嘉義縣朴子市",
     "經度": 120.254722222222,
     "緯度": 23.4655555555555,
     "電話": "(05)3799580",
     "服務類型": "Gogoro電動機車換電",
     "提供服務時段": "07:00-21:00"
    },
    {
     "站代號": "D434R",
     "站名": "鹿草站",
     "郵遞區號": "611",
     "地址": "嘉義縣鹿草鄉後堀村山仔腳59號",
     "地區": "嘉義縣鹿草鄉",
     "經度": 120.319166666666,
     "緯度": 23.4088888888888,
     "電話": "(05)3751219",
     "服務類型": "光陽電動機車換電2.0",
     "提供服務時段": "07:00-21:00"
    },
    {
     "站代號": "D434U",
     "站名": "大林中正路站",
     "郵遞區號": "622",
     "地址": "嘉義縣大林鎮中正路801號",
     "地區": "嘉義縣大林鎮",
     "經度": 120.461111111111,
     "緯度": 23.6097222222222,
     "電話": "(05)2659202",
     "服務類型": "電動機車充電",
     "提供服務時段": "07:00-21:00"
    },
    {
     "站代號": "D434U",
     "站名": "大林中正路站",
     "郵遞區號": "622",
     "地址": "嘉義縣大林鎮中正路801號",
     "地區": "嘉義縣大林鎮",
     "經度": 120.461111111111,
     "緯度": 23.6097222222222,
     "電話": "(05)2659202",
     "服務類型": "Gogoro電動機車換電",
     "提供服務時段": "07:00-21:00"
    },
    {
     "站代號": "D4350",
     "站名": "大林站",
     "郵遞區號": "622",
     "地址": "嘉義縣大林鎮中正路260號",
     "地區": "嘉義縣大林鎮",
     "經度": 120.45,
     "緯度": 23.5988888888888,
     "電話": "(05)2652049",
     "服務類型": "光陽電動機車換電2.0",
     "提供服務時段": "07:00-21:00"
    },
    {
     "站代號": "D4353",
     "站名": "民雄站",
     "郵遞區號": "621",
     "地址": "嘉義縣民雄鄉建國路二段329號",
     "地區": "嘉義縣民雄鄉",
     "經度": 120.433333333333,
     "緯度": 23.5508333333333,
     "電話": "(05)2262145",
     "服務類型": "Gogoro電動機車換電",
     "提供服務時段": "07:00-21:00"
    },
    {
     "站代號": "D4359",
     "站名": "南靖站",
     "郵遞區號": "608",
     "地址": "嘉義縣水上鄉三鎮路101-1號",
     "地區": "嘉義縣水上鄉",
     "經度": 120.389444444444,
     "緯度": 23.4197222222222,
     "電話": "(05)2682029",
     "服務類型": "Gogoro電動機車換電",
     "提供服務時段": "07:00-21:00"
    },
    {
     "站代號": "D435G",
     "站名": "大埔站",
     "郵遞區號": "607",
     "地址": "嘉義縣大埔鄉和平村雙溪14-3號",
     "地區": "嘉義縣大埔鄉",
     "經度": 120.598611111111,
     "緯度": 23.3013888888888,
     "電話": "(05)2521484",
     "服務類型": "光陽電動機車換電2.0",
     "提供服務時段": "07:00-18:00"
    },
    {
     "站代號": "D435H",
     "站名": "番路站",
     "郵遞區號": "602",
     "地址": "嘉義縣番路鄉下坑村下坑40-2號",
     "地區": "嘉義縣番路鄉",
     "經度": 120.537777777777,
     "緯度": 23.4708333333333,
     "電話": "(05)2592386",
     "服務類型": "光陽電動機車換電2.0",
     "提供服務時段": "07:00-21:00"
    },
    {
     "站代號": "D435R",
     "站名": "石卓站",
     "郵遞區號": "604",
     "地址": "嘉義縣竹崎鄉中和村永和1-1號",
     "地區": "嘉義縣竹崎鄉",
     "經度": 120.689444444444,
     "緯度": 23.4647222222222,
     "電話": "(05)2561944",
     "服務類型": "Gogoro電動機車換電",
     "提供服務時段": "07:30-18:00"
    },
    {
     "站代號": "D4360",
     "站名": "新港站",
     "郵遞區號": "616",
     "地址": "嘉義縣新港鄉菜公村菜公厝64-1號",
     "地區": "嘉義縣新港鄉",
     "經度": 120.346944444444,
     "緯度": 23.5508333333333,
     "電話": "(05)3742054",
     "服務類型": "電動機車充電",
     "提供服務時段": "00:00-24:00"
    },
    {
     "站代號": "D4360",
     "站名": "新港站",
     "郵遞區號": "616",
     "地址": "嘉義縣新港鄉菜公村菜公厝64-1號",
     "地區": "嘉義縣新港鄉",
     "經度": 120.346944444444,
     "緯度": 23.5508333333333,
     "電話": "(05)3742054",
     "服務類型": "光陽電動機車換電2.0",
     "提供服務時段": "00:00-24:00"
    },
    {
     "站代號": "D4378",
     "站名": "溪口站",
     "郵遞區號": "623",
     "地址": "嘉義縣溪口鄉溪東村民族西路１號",
     "地區": "嘉義縣溪口鄉",
     "經度": 120.400555555555,
     "緯度": 23.6025,
     "電話": "(05)2691700",
     "服務類型": "光陽電動機車換電2.0",
     "提供服務時段": "07:00-21:00"
    },
    {
     "站代號": "D4397",
     "站名": "嘉保站",
     "郵遞區號": "612",
     "地址": "嘉義縣太保市安仁里嘉朴東路1段116號",
     "地區": "嘉義縣太保市",
     "經度": 120.298888888888,
     "緯度": 23.4591666666666,
     "電話": "(05)3623558",
     "服務類型": "Gogoro電動機車換電",
     "提供服務時段": "07:00-21:00"
    },
    {
     "站代號": "D43X5",
     "站名": "阿里山新站",
     "郵遞區號": "605",
     "地址": "嘉義縣阿里山鄉南阿里山55-5號",
     "地區": "嘉義縣阿里山鄉",
     "經度": 120.792777777777,
     "緯度": 23.5041666666666,
     "電話": "(05)2679058",
     "服務類型": "Gogoro電動機車換電",
     "提供服務時段": "08:00-17:00"
    }
   ]